manageconfig/__init__.py
manageconfig/config.py
manageconfig-1.1.2.dist-info/licenses/LICENSE
manageconfig-1.1.2.dist-info/METADATA
manageconfig-1.1.2.dist-info/WHEEL
manageconfig-1.1.2.dist-info/top_level.txt
manageconfig-1.1.2.dist-info/RECORD
