Metadata-Version: 2.4
Name: manageconfig
Version: 1.1.2
Summary: Small package for working with config files
Author: Guyshe
Project-URL: Homepage, https://github.com/guyshe/manageconfig
Classifier: Programming Language :: Python :: 3
Classifier: License :: OSI Approved :: MIT License
Classifier: Operating System :: OS Independent
Requires-Python: >=3
License-File: LICENSE
Requires-Dist: PyYAML>=3.10
Dynamic: license-file
